aidex/__init__.py
aidex/app.py
aidex-0.1.1.dist-info/METADATA
aidex-0.1.1.dist-info/WHEEL
aidex-0.1.1.dist-info/entry_points.txt
aidex-0.1.1.dist-info/top_level.txt
aidex-0.1.1.dist-info/RECORD
